termrecord/__init__.py
termrecord/core.py
etermrecord-0.1.0.dist-info/METADATA
etermrecord-0.1.0.dist-info/WHEEL
etermrecord-0.1.0.dist-info/entry_points.txt
etermrecord-0.1.0.dist-info/RECORD
